pyuul/VolumeMaker.py
pyuul/__init__.py
pyuul/utils.py
pyuul/sources/__init__.py
pyuul/sources/globalVariables.py
pyuul/sources/hashings.py
pyuul-0.4.2.dist-info/METADATA
pyuul-0.4.2.dist-info/WHEEL
pyuul-0.4.2.dist-info/top_level.txt
pyuul-0.4.2.dist-info/RECORD
