Metadata-Version: 2.1
Name: pyuul
Version: 0.4.2
Summary: A library to convert biological structures in completely differentiable tensorial representations, such as point clouds or voxelized grids . Everything is deep learning ready
Home-page: https://bitbucket.org/grogdrinker/pyuul
Author: Gabriele Orlando
Author-email: orlando.gabriele89@gmail.com
Classifier: Programming Language :: Python :: 3
Classifier: License :: OSI Approved :: GNU Lesser General Public License v3 or later (LGPLv3+)
Classifier: Operating System :: OS Independent
Requires-Dist: torch
